jdFlatpakSnapshot/AboutDialog.py
jdFlatpakSnapshot/Constants.py
jdFlatpakSnapshot/Environment.py
jdFlatpakSnapshot/FlatpakHandler.py
jdFlatpakSnapshot/Functions.py
jdFlatpakSnapshot/ImportExport.py
jdFlatpakSnapshot/Languages.py
jdFlatpakSnapshot/MainWindow.py
jdFlatpakSnapshot/ProgressDialog.py
jdFlatpakSnapshot/Settings.py
jdFlatpakSnapshot/SettingsDialog.py
jdFlatpakSnapshot/Snapshot.py
jdFlatpakSnapshot/SnapshotCollection.py
jdFlatpakSnapshot/Types.py
jdFlatpakSnapshot/WelcomeDialog.py
jdFlatpakSnapshot/__init__.py
jdFlatpakSnapshot/__main__.py
jdFlatpakSnapshot/version.txt
jdFlatpakSnapshot/data/changelog.html
jdFlatpakSnapshot/data/translators.json
jdFlatpakSnapshot/icons/app-icon.svg
jdFlatpakSnapshot/icons/default-icon.svg
jdFlatpakSnapshot/translations/jdFlatpakSnapshot_de.qm
jdFlatpakSnapshot/translations/jdFlatpakSnapshot_nl.qm
jdFlatpakSnapshot/translations/jdFlatpakSnapshot_ru.qm
jdFlatpakSnapshot/translations/jdFlatpakSnapshot_tr.qm
jdFlatpakSnapshot/translations/jdFlatpakSnapshot_uk.qm
jdFlatpakSnapshot/ui_compiled/AboutDialog.py
jdFlatpakSnapshot/ui_compiled/MainWindow.py
jdFlatpakSnapshot/ui_compiled/ProgressDialog.py
jdFlatpakSnapshot/ui_compiled/SettingsDialog.py
jdFlatpakSnapshot/ui_compiled/WelcomeDialog.py
jdFlatpakSnapshot/ui_compiled/__init__.py
jdFlatpakSnapshot-2.2.dist-info/LICENSE
jdFlatpakSnapshot-2.2.dist-info/METADATA
jdFlatpakSnapshot-2.2.dist-info/WHEEL
jdFlatpakSnapshot-2.2.dist-info/entry_points.txt
jdFlatpakSnapshot-2.2.dist-info/top_level.txt
jdFlatpakSnapshot-2.2.dist-info/RECORD
